formantfeatures/FormantsExtract.py
formantfeatures/FormatsHDFread.py
formantfeatures/__init__.py
formantfeatures-1.0.3.dist-info/LICENSE.md
formantfeatures-1.0.3.dist-info/METADATA
formantfeatures-1.0.3.dist-info/WHEEL
formantfeatures-1.0.3.dist-info/top_level.txt
formantfeatures-1.0.3.dist-info/RECORD
